README.md
setup.py
linkedin_search_people_scraper/__init__.py
linkedin_search_people_scraper.egg-info/PKG-INFO
linkedin_search_people_scraper.egg-info/SOURCES.txt
linkedin_search_people_scraper.egg-info/dependency_links.txt
linkedin_search_people_scraper.egg-info/requires.txt
linkedin_search_people_scraper.egg-info/top_level.txt